add_agent/__init__.py
add_agent-0.1.0.dist-info/METADATA
add_agent-0.1.0.dist-info/WHEEL
add_agent-0.1.0.dist-info/entry_points.txt
add_agent-0.1.0.dist-info/RECORD
